jax_plugins/xla_rocm7/__init__.py
jax_plugins/xla_rocm7/commit_info.py
jax_plugins/xla_rocm7/version.py
jax_plugins/xla_rocm7/xla_rocm_plugin.so
jax_rocm7_pjrt-0.7.1.dist-info/METADATA
jax_rocm7_pjrt-0.7.1.dist-info/WHEEL
jax_rocm7_pjrt-0.7.1.dist-info/entry_points.txt
jax_rocm7_pjrt-0.7.1.dist-info/top_level.txt
jax_rocm7_pjrt-0.7.1.dist-info/RECORD
