Metadata-Version: 2.4
Name: jax-rocm7-pjrt
Version: 0.7.1
Summary: JAX XLA PJRT Plugin for AMD GPUs (ROCm:unknown)
Home-page: https://github.com/jax-ml/jax
Author: Ruturaj4
Author-email: Ruturaj.Vaidya@amd.com
License: Apache-2.0
Classifier: Development Status :: 3 - Alpha
Classifier: Programming Language :: Python :: 3
Dynamic: author
Dynamic: author-email
Dynamic: classifier
Dynamic: description-content-type
Dynamic: home-page
Dynamic: license
Dynamic: summary
